LICENSE
README.md
setup.py
microhook/__init__.py
microhook/microhook.py
microhook.egg-info/PKG-INFO
microhook.egg-info/SOURCES.txt
microhook.egg-info/dependency_links.txt
microhook.egg-info/top_level.txt
scripts/microhook